paste/PASTE.py
paste/__init__.py
paste/helper.py
paste/visualization.py
paste_bio-1.3.0.dist-info/LICENSE
paste_bio-1.3.0.dist-info/METADATA
paste_bio-1.3.0.dist-info/WHEEL
paste_bio-1.3.0.dist-info/top_level.txt
paste_bio-1.3.0.dist-info/RECORD
