Metadata-Version: 2.1
Name: paste-bio
Version: 1.3.0
Summary: A computational method to align and integrate spatial transcriptomics experiments.
Home-page: https://github.com/raphael-group/paste
Author: Max Land
Author-email: max.ruikang.land@gmail.com
Project-URL: Bug Tracker, https://github.com/raphael-group/paste/issues
Classifier: Programming Language :: Python :: 3
Classifier: License :: OSI Approved :: BSD License
Classifier: Operating System :: OS Independent
Requires-Python: >=3.6
License-File: LICENSE
